{
	"schema": [
		{
			"actionable": true,
			"directionType": "directed",
			"isBoolean": false,
			"cloneEachTimeStep": true,
			"category": "feelingCategory",
			"types": [
				"bonding"
			],
			"defaultValue": 0,
			"maxValue": 100,
			"minValue": -100
		},
		{
			"actionable": false,
			"directionType": "undirected",
			"isBoolean": true,
			"cloneEachTimeStep": true,
			"category": "charLabel",
			"types": [
				"anyone",
				"jesse",
				"rowan",
				"chad",
				"stacy",
				"alan"
			],
			"defaultValue": false
		},
		{
			"actionable": true,
			"directionType": "directed",
			"isBoolean": false,
			"cloneEachTimeStep": true,
			"category": "interactionRecord",
			"types": [
				"timespersuadedtododrug",
				"timespersuadedtodrink",
				"timescomplimented"
			],
			"defaultValue": 0,
			"maxValue": 5,
			"minValue": 0
		},
		{
			"actionable": true,
			"directionType": "undirected",
			"isBoolean": true,
			"cloneEachTimeStep": true,
			"duration": 100,
			"category": "statusLabel",
			"types": [
				"interacted",
				"ondrug",
				"persuadedtodrink",
				"persuadedtogethigh"
			],
			"defaultValue": false
		},
		{
			"actionable": true,
			"directionType": "undirected",
			"isBoolean": false,
			"cloneEachTimeStep": true,
			"category": "charAttributes",
			"types": [
				"fame",
				"drunkenness",
				"ondrug"
			],
			"defaultValue": 0,
			"maxValue": 100,
			"minValue": 0
		}
	]
}